rate_table_images/__init__.py
rate_table_images/rate_table_images.py
rate_table_images-0.0.1.dist-info/METADATA
rate_table_images-0.0.1.dist-info/WHEEL
rate_table_images-0.0.1.dist-info/entry_points.txt
rate_table_images-0.0.1.dist-info/top_level.txt
rate_table_images-0.0.1.dist-info/RECORD
