Metadata-Version: 2.1
Name: rate-table-images
Version: 0.0.1
Summary: Get the Rate Table Images
Home-page: https://github.com/A284viral/protections_v1
Author: Aviral Srivastava
Author-email: aviralsrivastava284@gmail.com
Classifier: Programming Language :: Python :: 3
Classifier: License :: OSI Approved :: MIT License
Classifier: Operating System :: OS Independent
Requires-Python: >=3.6
Requires-Dist: pandas
Requires-Dist: xlsxwriter
Requires-Dist: matplotlib
Requires-Dist: dataframe-image
